{
    "Pres": [
        "Demand patterns are shifting.",
        "Market share is expanding.",
        "Product innovation is accelerating.",
        "Technological advancements are enabling new revenue streams.",
        "Strategic partnerships are forming.",
        "Customer retention rates are improving.",
        "Research and development investment is growing.",
        "Product portfolio is broadening.",
        "Market volatility is rising.",
        "Technological disruption is accelerating.",
        "Operational efficiencies are improving.",
        "Strategic initiatives are progressing.",
        "Innovation pipelines are strengthening.",
        "Debt levels are manageable.",
        "Cash flow generation is stable.",
        "Growth investments are prioritized.",
        "Debt reduction is prioritized.",
        "Operational efficiency is emphasized.",
        "Cost reduction initiatives are implemented.",
        "Cash flow generation is strong.",
        "Liquidity positions are robust.",
        "Risk mitigation strategies are employed.",
        "Financial risk exposure is minimized.",
        "Strategic flexibility is maintained.",
        "Economic uncertainty influences planning.",
        "High-return projects are favored.",
        "Balance sheet strength is preserved."
    ],
    "Q&A1": [
        "Growth opportunities are emerging.",
        "Product innovation is accelerating.",
        "Cash flow generation is strong.",
        "Operational efficiencies are improving."
    ],
    "Q&A2": [
        "Customer retention rates are improving.",
        "Strategic initiatives are progressing.",
        "Operational efficiency is emphasized."
    ],
    "Q&A3": [
        "Sales cycle length is shortening.",
        "Customer retention rates are improving.",
        "Growth opportunities are emerging.",
        "Market share is expanding."
    ],
    "Q&A4": [
        "Cash flow generation is strong.",
        "Operational efficiencies are improving.",
        "Currency exchange rates are fluctuating."
    ],
    "Q&A5": [
        "Demand for digital solutions is surging.",
        "Value-added services are expanding.",
        "Strategic partnerships are forming."
    ],
    "Q&A6": [
        "Operational efficiencies are improving.",
        "Cash flow generation is strong."
    ],
    "Q&A7": [
        "Sales cycle length is shortening.",
        "Cost reduction initiatives are implemented.",
        "Liquidity positions are robust.",
        "Financial risk exposure is minimized."
    ]
}