{
    "Pres": [
        "Market share is expanding.",
        "Growth investments are prioritized.",
        "Strategic partnerships are forming.",
        "Product portfolio is broadening.",
        "Customer base is diversifying.",
        "Technological advancements are enabling new revenue streams.",
        "Operational efficiency is emphasized.",
        "Cost reduction initiatives are implemented.",
        "Cash flow generation is strong.",
        "Liquidity positions are robust.",
        "Demand for digital solutions is surging.",
        "Customer retention rates are improving."
    ],
    "Q&A1": [
        "Market share is expanding.",
        "Customer retention rates are improving."
    ],
    "Q&A2": [
        "Market conditions are volatile.",
        "Growth opportunities are emerging."
    ],
    "Q&A3": [
        "Growth investments are prioritized.",
        "Dividend distributions are increasing.",
        "Share buybacks are utilized."
    ],
    "Q&A4": [
        "Liquidity positions are robust.",
        "Cash flow generation is strong."
    ],
    "Q&A5": [
        "Premium pricing acceptance is variable."
    ],
    "Q&A6": [
        "Market share is expanding.",
        "Technological advancements are enabling new revenue streams."
    ],
    "Q&A7": [
        "Operational efficiency is emphasized.",
        "Cost reduction initiatives are implemented."
    ],
    "Q&A8": [],
    "Q&A9": [
        "Market share is expanding.",
        "Growth opportunities are emerging."
    ]
}