{
    "Pres": [
        "Labor expenses are increasing.",
        "Regulatory compliance costs are mounting.",
        "Cost pressures are mounting.",
        "Pricing power is diminishing.",
        "Profit margins are compressing.",
        "Market share is expanding.",
        "Growth opportunities are emerging.",
        "Economic uncertainty is rising.",
        "Geopolitical risks are amplifying.",
        "Regulatory scrutiny is intensifying.",
        "Balance sheet strength is preserved.",
        "Liquidity positions are robust.",
        "Cash flow generation is strong.",
        "Inflationary pressures are persisting.",
        "Consumer demand is fluctuating.",
        "Customer acquisition costs are rising."
    ],
    "Q&A1": [
        "Dividend distributions are increasing.",
        "Share buybacks are utilized.",
        "Balance sheet strength is preserved.",
        "Strategic flexibility is maintained.",
        "Economic uncertainty influences planning."
    ],
    "Q&A2": [
        "Interest rates are fluctuating unpredictably.",
        "Demand patterns are shifting.",
        "Pricing power is fluctuating."
    ],
    "Q&A3": [],
    "Q&A4": [
        "Economic uncertainty is rising.",
        "Geopolitical risks are amplifying.",
        "Interest rates are fluctuating unpredictably.",
        "Market conditions are volatile."
    ],
    "Q&A5": [
        "Pricing power is diminishing.",
        "Profit margins are compressing.",
        "Economic uncertainty influences planning.",
        "Inflationary pressures affect costs."
    ],
    "Q&A6": [
        "Regulatory scrutiny is intensifying.",
        "Market share is expanding.",
        "Growth opportunities are emerging.",
        "Competition is intensifying."
    ],
    "Q&A7": [
        "Market share is expanding.",
        "International expansion is accelerating.",
        "Technological innovation is accelerating."
    ],
    "Q&A8": [
        "Growth opportunities are emerging.",
        "Cost optimization is a continuous focus.",
        "Operational efficiency is emphasized.",
        "Strategic initiatives are progressing."
    ],
    "Q&A9": [
        "Consumer demand patterns are shifting rapidly.",
        "Market volatility is rising."
    ],
    "Q&A10": [
        "Competition is intensifying.",
        "Pricing power is diminishing.",
        "Market conditions are volatile."
    ],
    "Q&A11": [
        "Strategic initiatives are progressing.",
        "Cost reduction initiatives are implemented.",
        "Growth opportunities are emerging."
    ]
}