{
    "Pres": [
        "Market share is expanding.",
        "Demand for digital solutions is surging.",
        "Technological innovation is accelerating.",
        "Operational efficiencies are improving.",
        "Strategic initiatives are progressing.",
        "Growth investments are prioritized.",
        "Dividend distributions are increasing.",
        "Share buybacks are utilized.",
        "Leverage ratios are maintained.",
        "Cash flow generation is strong.",
        "Liquidity positions are robust.",
        "Risk mitigation strategies are employed.",
        "Financial risk exposure is minimized.",
        "Economic uncertainty influences planning.",
        "Balance sheet strength is preserved."
    ],
    "Q&A1": [
        "Inflationary pressures are persisting.",
        "Economic uncertainty is rising.",
        "Growth opportunities are emerging.",
        "Liquidity positions are robust.",
        "Strategic flexibility is maintained."
    ],
    "Q&A2": [
        "Labor expenses are increasing.",
        "Cost pressures are mounting.",
        "Growth opportunities are emerging."
    ],
    "Q&A3": [
        "Technological innovation is accelerating.",
        "Competition is intensifying.",
        "Strategic partnerships are forming.",
        "Product portfolio is broadening."
    ],
    "Q&A4": [
        "Customer acquisition cost is rising.",
        "Supply chain disruptions are occurring."
    ],
    "Q&A5": [
        "Customer acquisition cost is rising.",
        "Regulatory environment is evolving."
    ],
    "Q&A6": [
        "Technological disruption is accelerating.",
        "Competition is intensifying."
    ],
    "Q&A7": [
        "Competition is intensifying.",
        "Regulatory environment is evolving.",
        "Strategic flexibility is maintained."
    ],
    "Q&A8": [
        "Growth opportunities are emerging.",
        "Liquidity positions are robust."
    ],
    "Q&A9": [
        "Liquidity positions are robust.",
        "Strategic flexibility is maintained.",
        "Growth investments are prioritized."
    ],
    "Q&A10": [],
    "Q&A11": [],
    "Q&A12": [
        "Inflationary pressures are persisting.",
        "Economic uncertainty is rising.",
        "Risk mitigation strategies are employed."
    ]
}