{
    "Pres": [
        "Market share is expanding.",
        "Product innovation is accelerating.",
        "Research and development investment is growing.",
        "Strategic partnerships are forming.",
        "International expansion is accelerating.",
        "Operational efficiencies are improving.",
        "Growth investments are prioritized.",
        "Dividend distributions are increasing.",
        "Share buybacks are utilized."
    ],
    "Q&A1": [],
    "Q&A2": [
        "Pricing pressures are mounting.",
        "Competition is intensifying.",
        "Product innovation is accelerating."
    ],
    "Q&A3": [
        "Technological advancements are enabling new revenue streams.",
        "Product innovation is accelerating."
    ],
    "Q&A4": [
        "Product innovation is accelerating.",
        "Market share is expanding."
    ],
    "Q&A5": [
        "Product innovation is accelerating."
    ],
    "Q&A6": [
        "Production output is scalable.",
        "Product innovation is accelerating."
    ],
    "Q&A7": [
        "Regulatory environment is evolving."
    ],
    "Q&A8": [
        "Product innovation is accelerating."
    ],
    "Q&A9": [
        "Pricing pressures are mounting."
    ],
    "Q&A10": [
        "Market share is expanding.",
        "Regulatory environment is evolving."
    ],
    "Q&A11": [
        "Product innovation is accelerating.",
        "Growth opportunities are emerging."
    ],
    "Q&A12": [
        "Research and development investment is growing.",
        "Product innovation is accelerating."
    ],
    "Q&A13": [
        "Technological advancements are enabling new revenue streams.",
        "Product innovation is accelerating."
    ]
}